_rsa_util.abi3.so
pygo_jwt-0.0.9.dist-info/top_level.txt
pygo_jwt-0.0.9.dist-info/METADATA
pygo_jwt-0.0.9.dist-info/WHEEL
pygo_jwt-0.0.9.dist-info/RECORD
pygo_tools_lib/wrapper_util.py
pygo_tools_lib/__init__.py
pygo_jwt/time_util.py
pygo_jwt/errors.py
pygo_jwt/__init__.py
pygo_jwt/jwt_util.py
pygo_jwt/b64_util.py
pygo_jwt/wrapper.py
pygo_jwt/go/go.mod
pygo_jwt/go/wrapper_util.go
pygo_jwt/go/wrapper_util.h
pygo_jwt/go/wrapper.go
pygo_jwt/go/Makefile
pygo_jwt/go/core/sign_verify.go
pygo_jwt/go/core/misc.go
pygo_jwt/go/core/public_factory.go
pygo_jwt/go/core/conversions.go
pygo_jwt/go/core/private_factory.go
pygo_jwt/go/util/type_alias.go
pygo_jwt/go/util/hash_util.go
pygo_jwt/go/util/str_util.go
pygo_jwt/go/util/json_util.go
pygo_jwt/go/util/b64_util.go
pygo_jwt/lib/librsautil.so
