Metadata-Version: 2.1
Name: pygo-jwt
Version: 0.0.9
Summary: Encode and Decode RS256 JSON Web Tokens with Python and Go
Author-email: Rajan Khullar <rkhullar03@gmail.com>
License: MIT NON-AI License
Project-URL: Repository, https://github.com/rkhullar/python-libraries/tree/main/pygo-jwt
Keywords: python,golang,jwt,rsa
Requires-Python: <4.0,>=3.10
